<?xml version="1.0" encoding="utf-8"?>
<!DOCTYPE hibernate-mapping PUBLIC "-//Hibernate/Hibernate Mapping DTD 3.0//EN"
"http://hibernate.sourceforge.net/hibernate-mapping-3.0.dtd">
<!-- 
    Mapping file autogenerated by MyEclipse Persistence Tools
-->
<hibernate-mapping>
    <class name="com.jxoa.manager.personalOffice.bean.EmFiles" table="em_files" >
        <id name="id" type="java.lang.String">
            <column name="id" length="32" />
            <generator class="uuid.hex"></generator>
        </id>
        <property name="efName" type="java.lang.String">
            <column name="ef_name" length="50">
                <comment>原文件名</comment>
            </column>
        </property>
        <property name="efNewName" type="java.lang.String">
            <column name="ef_new_name" length="32">
                <comment>保存时的文件名称,UUID</comment>
            </column>
        </property>
        <property name="efExt" type="java.lang.String">
            <column name="ef_ext" length="50">
                <comment>后缀</comment>
            </column>
        </property>
        <property name="efSize" type="java.lang.Integer">
            <column name="ef_size">
                <comment>大小</comment>
            </column>
        </property>
        <property name="efNum" type="java.lang.Integer">
            <column name="ef_num">
                <comment>引用量</comment>
            </column>
        </property>
        <set name="emOutboxFiles" inverse="true">
            <key>
                <column name="of_efid" length="32">
                    <comment>附件表ID</comment>
                </column>
            </key>
            <one-to-many class="com.jxoa.manager.personalOffice.bean.EmOutboxFile" />
        </set>
        <set name="emInboxFiles" inverse="true">
            <key>
                <column name="if_efid" length="32">
                    <comment>附件表ID</comment>
                </column>
            </key>
            <one-to-many class="com.jxoa.manager.personalOffice.bean.EmInboxFile" />
        </set>
    </class>
</hibernate-mapping>
