<?xml version="1.0" encoding="utf-8"?>
<!DOCTYPE hibernate-mapping PUBLIC "-//Hibernate/Hibernate Mapping DTD 3.0//EN"
"http://hibernate.sourceforge.net/hibernate-mapping-3.0.dtd">
<!-- 
    Mapping file autogenerated by MyEclipse Persistence Tools
-->
<hibernate-mapping>
    <class name="com.jxoa.manager.coordination.bean.XtNoticeContent" table="xt_notice_content" >
        <id name="noticeId" type="java.lang.String">
            <column name="notice_id" length="32" />
            <generator class="assigned" />
        </id>
        <property name="noticeContent" type="java.lang.String">
            <column name="notice_content" length="65535">
                <comment>通知详细内容</comment>
            </column>
        </property>
        <property name="userIds" type="java.lang.String">
            <column name="userIds" length="65535">
                <comment>接收用户id,多个，隔开</comment>
            </column>
        </property>
        <property name="deptIds" type="java.lang.String">
            <column name="deptIds" length="65535">
                <comment>接收部门id,多个，隔开</comment>
            </column>
        </property>
    </class>
</hibernate-mapping>
